nonebot_plugin_weather_rank/__init__.py
nonebot_plugin_weather_rank/config.py
nonebot_plugin_weather_rank/utils/addition_for_htmlrender.py
nonebot_plugin_weather_rank/utils/constant.py
nonebot_plugin_weather_rank/utils/model.py
nonebot_plugin_weather_rank/utils/schema.py
nonebot_plugin_weather_rank/utils/services.py
nonebot_plugin_weather_rank/weather_rank/__init__.py
nonebot_plugin_weather_rank/weather_rank/help.md
nonebot_plugin_weather_rank/weather_rank/templates/fonts/ComicShannsMonoNerdFont-Regular.otf
nonebot_plugin_weather_rank/weather_rank/templates/fonts/miaozi-meiweiti-2.ttf
nonebot_plugin_weather_rank/weather_rank/templates/images/clr.png
nonebot_plugin_weather_rank/weather_rank/templates/images/weather_bg.png
nonebot_plugin_weather_rank/weather_rank/templates/rank_card.html
nonebot_plugin_weather_rank/weather_rank/templates/rank_card.html.jinja2
nonebot_plugin_weather_rank/weather_rank/templates/weather_card.html
nonebot_plugin_weather_rank/weather_rank/templates/weather_card.html.jinja2
nonebot_plugin_weather_rank-0.1.9.dist-info/LICENSE
nonebot_plugin_weather_rank-0.1.9.dist-info/METADATA
nonebot_plugin_weather_rank-0.1.9.dist-info/WHEEL
nonebot_plugin_weather_rank-0.1.9.dist-info/RECORD
