Metadata-Version: 2.3
Name: nonebot-plugin-weather-rank
Version: 0.1.9
Summary: 一个比较群友地区天气温度的插件
License: MIT
Author: hanasa2023
Author-email: hanasakayui2022@gmail.com
Requires-Python: >=3.9,<4.0
Classifier: License :: OSI Approved :: MIT License
Classifier: Programming Language :: Python :: 3
Classifier: Programming Language :: Python :: 3.9
Classifier: Programming Language :: Python :: 3.10
Classifier: Programming Language :: Python :: 3.11
Classifier: Programming Language :: Python :: 3.12
Classifier: Programming Language :: Python :: 3.13
Requires-Dist: beautifulsoup4 (>=4.12.3)
Requires-Dist: httpx (>=0.27.0)
Requires-Dist: nonebot-adapter-onebot (>=2.1.0)
Requires-Dist: nonebot-plugin-alconna (>=0.52.2)
Requires-Dist: nonebot-plugin-apscheduler (>=0.5.0,<0.6.0)
Requires-Dist: nonebot-plugin-htmlrender (>=0.3.5)
Requires-Dist: nonebot-plugin-localstore (>=0.7.1,<0.8.0)
Requires-Dist: nonebot2 (>=2.3.2)
Requires-Dist: pydantic (>=1.0,<3.0.0)
Requires-Dist: tortoise-orm[asyncpg] (>=0.21.6,<0.22.0)
